linkerbot_sdk/__init__.py
linkerbot_sdk/linkerbot.py
linkerbot_sdk/test.py
linkerbot-0.1.11.dist-info/LICENSE
linkerbot-0.1.11.dist-info/METADATA
linkerbot-0.1.11.dist-info/WHEEL
linkerbot-0.1.11.dist-info/top_level.txt
linkerbot-0.1.11.dist-info/RECORD
