Metadata-Version: 2.1
Name: linkerbot
Version: 0.1.11
Summary: 灵心巧手相关的SDK
Home-page: https://github.com/yourusername/linkerbot-sdk
Author: LinkerBot
Author-email: 2424028621@example.com
Classifier: Programming Language :: Python :: 3
Classifier: License :: OSI Approved :: MIT License
Classifier: Operating System :: OS Independent
Requires-Python: >=3.6
License-File: LICENSE
Requires-Dist: requests>=2.25.1
Requires-Dist: tqdm>=4.65.0
